setup.py
huaiyu_distributions/Binomialdistribution.py
huaiyu_distributions/Gaussiandistribution.py
huaiyu_distributions/Generaldistribution.py
huaiyu_distributions/__init__.py
huaiyu_distributions.egg-info/PKG-INFO
huaiyu_distributions.egg-info/SOURCES.txt
huaiyu_distributions.egg-info/dependency_links.txt
huaiyu_distributions.egg-info/not-zip-safe
huaiyu_distributions.egg-info/top_level.txt